README.rst
pymprog.py
setup.py
pymprog.egg-info/PKG-INFO
pymprog.egg-info/SOURCES.txt
pymprog.egg-info/dependency_links.txt
pymprog.egg-info/requires.txt
pymprog.egg-info/top_level.txt