Metadata-Version: 1.1
Name: pymprog
Version: 1.1.1
Summary: An easy and flexible mathematical programming environment for Python
Home-page: http://pymprog.sourceforge.net/
Author: Yingjie Lan
Author-email: ylan@pku.edu.cn
License: GPL
Keywords: glpk math optimization LP MIP
Platform: UNKNOWN
Classifier: Development Status :: 5 - Production/Stable
Classifier: Intended Audience :: Science/Research
Classifier: Intended Audience :: Education
Classifier: License :: OSI Approved :: GNU General Public License (GPL)
Classifier: Programming Language :: Python
Classifier: Programming Language :: Python :: 3
Classifier: Operating System :: OS Independent
Classifier: Topic :: Scientific/Engineering :: Mathematics
